{
  "variants": {
    "facing=north,lit=true": {
      "model": "lotm:block/monster_domain"
    },
    "facing=south,lit=true": {
      "model": "lotm:block/monster_domain",
      "y": 180
    },
    "facing=west,lit=true": {
      "model": "lotm:block/monster_domain",
      "y": 270
    },
    "facing=east,lit=true": {
      "model": "lotm:block/monster_domain",
      "y": 90
    },
    "facing=north,lit=false": {
      "model": "lotm:block/monster_domain_decay"
    },
    "facing=south,lit=false": {
      "model": "lotm:block/monster_domain_decay",
      "y": 180
    },
    "facing=west,lit=false": {
      "model": "lotm:block/monster_domain_decay",
      "y": 270
    },
    "facing=east,lit=false": {
      "model": "lotm:block/monster_domain_decay",
      "y": 90
    }
  }
}